MANIFEST.in
requirements.txt
setup.cfg
setup.py
bin/catapult
catapult/__init__.py
catapult/version.py
catapult/deploy/__init__.py
catapult/deploy/blocker.py
catapult/deploy/bullet.py
catapult/deploy/constants.py
catapult/deploy/factory.py
catapult/deploy/locker.py
catapult/deploy/logger.py
catapult/deploy/modules.py
catapult/deploy/notifier.py
catapult/deploy/paths.py
catapult/deploy/recipes.py
catapult/deploy/ssh.py
catapult/deploy/storage.py
catapult/deploy/phases/__init__.py
catapult/deploy/phases/building.py
catapult/deploy/phases/checking.py
catapult/deploy/phases/cleaning.py
catapult/deploy/phases/configuring.py
catapult/deploy/phases/ending.py
catapult/deploy/phases/installing.py
catapult/deploy/phases/locking.py
catapult/deploy/phases/maintaining.py
catapult/deploy/phases/releasing.py
catapult/deploy/phases/starting.py
catapult/library/__init__.py
catapult/library/exceptions.py
catapult/library/helpers.py
catapult/library/maintain.py
catapult/library/parsers.py
catapult/library/renders.py
catapult/library/transformers.py
catapult/library/transports.py
catapult/library/validators.py
catapult/loggers/__init__.py
catapult/loggers/cli.py
catapult/loggers/server.py
catapult/modules/__init__.py
catapult/modules/balancer.py
catapult/modules/constants.py
catapult/modules/library.py
catapult/modules/normalizers.py
catapult/modules/crontab/__init__.py
catapult/modules/crontab/module.py
catapult/modules/docker/__init__.py
catapult/modules/docker/module.py
catapult/modules/nginx/__init__.py
catapult/modules/nginx/module.py
catapult/modules/pm2/__init__.py
catapult/modules/pm2/module.py
catapult/modules/supervisor/__init__.py
catapult/modules/supervisor/module.py
catapult/modules/systemd/__init__.py
catapult/modules/systemd/module.py
catapult/server/__init__.py
catapult/server/builders.py
catapult/server/constants.py
catapult/server/killer.py
catapult/server/library.py
catapult/server/repository.py
catapult/server/processes/__init__.py
catapult3.egg-info/PKG-INFO
catapult3.egg-info/SOURCES.txt
catapult3.egg-info/dependency_links.txt
catapult3.egg-info/not-zip-safe
catapult3.egg-info/requires.txt
catapult3.egg-info/top_level.txt