Metadata-Version: 1.0
Name: catapult3
Version: 3.4
Summary: Catapult - DevOps Deployment System
Home-page: UNKNOWN
Author: Artemiy Pulyavin
Author-email: artemiy@pulyavin.ru
License: LGPLv3
Keywords: deploy
Platform: UNKNOWN
